{
    "cameras": [
        {
            "camera_id": 0,
            "floor_id": 0,
            "camera_parameter_path": "/data/TownCentre/camera_parameter.json",
            "uri": "/data/TownCentre/TownCentreXVID.avi",
            "mask": "/data/TownCentre/TownCentreMask.png",
            "frame_skip": 4
        }
    ],
    "detector": {
        "detector_config": {
            "scaler": {
                "range": [0, 12]
            }
        }
    },
    "caffe_taggers": [
        {
            "caffe_wrapper": {
                "meanfile_path": "scouter-resources/caffe/gender_kg/mean",
                "model_path": "scouter-resources/caffe/gender_kg/model",
                "architecture_path": "scouter-resources/caffe/gender_kg/arch",
                "tasks": [
                    {"name": "gender", "label_mapping": ["Female", "Male"]}
                ],
                "gpu_mode": true
            },
            "input": {
                "base_width": 224,
                "offset_x": 0,
                "offset_y": -5,
                "width": 224,
                "height": 373,
                "resize_width": 224,
                "resize_height": 224
            }
        }

    ],
    "fake_interval": 200,
    "tick_interval": 300,
    "mm_per_unitdistance": 1000,
    "imshow": ["detect", "integrate"],
    "jpegshow": ["detect", "integrate"],
    "mjpegserv": {
        "port": 10080
    }
}
